zathura_rpc/__init__.py
zathura_rpc/__main__.py
zathura_rpc-0.0.2.dist-info/LICENSE
zathura_rpc-0.0.2.dist-info/METADATA
zathura_rpc-0.0.2.dist-info/WHEEL
zathura_rpc-0.0.2.dist-info/entry_points.txt
zathura_rpc-0.0.2.dist-info/RECORD
