Metadata-Version: 2.1
Name: zathura-rpc
Version: 0.0.2
Summary: Discord RPC client for zathura.
License: GPL3
Author: DemonKingSwarn
Author-email: rockingswarn@gmail.com
Requires-Python: >=3.10,<4.0
Classifier: License :: Other/Proprietary License
Classifier: Programming Language :: Python :: 3
Classifier: Programming Language :: Python :: 3.10
Classifier: Programming Language :: Python :: 3.11
Requires-Dist: pypresence (>=4.2.1,<5.0.0)
